xmlasdict/__init__.py
xmlasdict/__main__.py
xmlasdict/__version__.py
xmlasdict/exceptions.py
xmlasdict/parser.py
xmlasdict/wrapper.py
xmlasdict-0.2.2.dist-info/LICENSE
xmlasdict-0.2.2.dist-info/METADATA
xmlasdict-0.2.2.dist-info/WHEEL
xmlasdict-0.2.2.dist-info/entry_points.txt
xmlasdict-0.2.2.dist-info/top_level.txt
xmlasdict-0.2.2.dist-info/RECORD
