Metadata-Version: 2.1
Name: xmlasdict
Version: 0.2.2
Summary: python library to read xml DOM trees as dicts (with iter and gettattribute behaviour)
Home-page: https://github.com/vliz-be-opsci/py-xmlasdict
Author: Marc Portier
Author-email: marc.portier@gmail.com
License: MIT
Platform: UNKNOWN
Classifier: License :: OSI Approved :: MIT License
Classifier: Programming Language :: Python
Classifier: Programming Language :: Python :: 3.8
License-File: LICENSE
Provides-Extra: dev
